CHANGELOG.md
pywgkey/__init__.py
pywgkey/__main__.py
pywgkey/config.py
pywgkey/key.py
pywgkey/utils.py
tests/__init__.py
tests/test_pywgkey.py
pywgkey-1.0.0.dist-info/LICENSE
pywgkey-1.0.0.dist-info/WHEEL
pywgkey-1.0.0.dist-info/METADATA
pywgkey-1.0.0.dist-info/RECORD
