Metadata-Version: 2.1
Name: pywgkey
Version: 1.0.0
Summary: A simple WireGuard key generator writen in python.
Home-page: https://github.com/polluxtroy3758/pywgkey
License: MIT
Author: polluxtroy3758
Author-email: 2147396+polluxtroy3758@users.noreply.github.com
Requires-Python: >=3.7,<4.0
Classifier: License :: OSI Approved :: MIT License
Classifier: Operating System :: OS Independent
Classifier: Programming Language :: Python
Classifier: Programming Language :: Python :: 3
Classifier: Programming Language :: Python :: 3 :: Only
Classifier: Programming Language :: Python :: 3.10
Classifier: Programming Language :: Python :: 3.7
Classifier: Programming Language :: Python :: 3.8
Classifier: Programming Language :: Python :: 3.9
Classifier: Topic :: Security
Classifier: Topic :: Security :: Cryptography
Classifier: Topic :: Software Development
Classifier: Topic :: Software Development :: Libraries
Classifier: Topic :: Software Development :: Libraries :: Python Modules
Classifier: Topic :: Utilities
Requires-Dist: PyNaCl (>=1.5.0,<2.0.0)
Requires-Dist: click (>=8.0.4,<9.0.0)
Project-URL: Repository, https://github.com/polluxtroy3758/pywgkey
